iperf3_lib/__init__.py
iperf3_lib/capabilities.py
iperf3_lib/config.py
iperf3_lib/exceptions.py
iperf3_lib/iperf_client.py
iperf3_lib/iperf_server.py
iperf3_lib/result.py
iperf3_lib/ffi/__init__.py
iperf3_lib/ffi/api.py
iperf3_lib/ffi/symbols.py
iperf3_lib-0.1.0.dist-info/METADATA
iperf3_lib-0.1.0.dist-info/WHEEL
iperf3_lib-0.1.0.dist-info/licenses/LICENSE
iperf3_lib-0.1.0.dist-info/RECORD
