Metadata-Version: 2.4
Name: iperf3-lib
Version: 0.1.0
Summary: Modern Python wrapper for iperf3 using cffi (libiperf), with async support.
Project-URL: Homepage, https://github.com/dariuszpanas/iperf3-lib
Project-URL: Documentation, https://github.com/dariuszpanas/iperf3-lib/tree/main/docs
Project-URL: Repository, https://github.com/dariuszpanas/iperf3-lib
Project-URL: Issues, https://github.com/dariuszpanas/iperf3-lib/issues
Author: Dariusz Panas
License-Expression: MIT
License-File: LICENSE
Keywords: MPTCP,SCTP,async,benchmark,cffi,iperf3,network,throughput
Classifier: Development Status :: 4 - Beta
Classifier: Environment :: Console
Classifier: Intended Audience :: Developers
Classifier: Intended Audience :: System Administrators
Classifier: License :: OSI Approved :: MIT License
Classifier: Operating System :: OS Independent
Classifier: Programming Language :: Python :: 3
Classifier: Programming Language :: Python :: 3.12
Classifier: Programming Language :: Python :: 3.13
Classifier: Topic :: Software Development :: Libraries :: Python Modules
Classifier: Topic :: System :: Benchmark
Classifier: Topic :: System :: Networking
Requires-Python: >=3.12
Requires-Dist: cffi>=1.16
Requires-Dist: pydantic>=2.8
